LICENSE
README.md
powderbooking/__init__.py
powderbooking/database.py
powderbooking/models.py
powderbooking/query.py
powderbooking/utils.py
powderbooking-0.6.0.dist-info/LICENSE
powderbooking-0.6.0.dist-info/WHEEL
powderbooking-0.6.0.dist-info/METADATA
powderbooking-0.6.0.dist-info/RECORD
