Metadata-Version: 2.1
Name: powderbooking
Version: 0.6.0
Summary: RESTful API backend for the Powderbooking application
License: Apache-2.0
Author: Michael Kemna
Author-email: michael.kemna@gmail.com
Requires-Python: >=3.7,<4.0
Classifier: Development Status :: 3 - Alpha
Classifier: License :: OSI Approved :: Apache Software License
Classifier: Programming Language :: Python :: 3
Classifier: Programming Language :: Python :: 3.6
Classifier: Programming Language :: Python :: 3.7
Classifier: Programming Language :: Python :: 3.8
Classifier: Programming Language :: Python :: 3.9
Classifier: Topic :: Database :: Database Engines/Servers
Requires-Dist: SQLalchemy (>=1.3.19,<2.0.0)
